arcor2_mocks/VERSION
arcor2_mocks/__init__.py
arcor2_mocks/exceptions_asset.py
arcor2_mocks/exceptions_project.py
arcor2_mocks/py.typed
arcor2_mocks/scripts/__init__.py
arcor2_mocks/scripts/mock_asset.py
arcor2_mocks/scripts/mock_project.py
arcor2_mocks-1.1.0.dist-info/METADATA
arcor2_mocks-1.1.0.dist-info/WHEEL
arcor2_mocks-1.1.0.dist-info/entry_points.txt
arcor2_mocks-1.1.0.dist-info/namespace_packages.txt
arcor2_mocks-1.1.0.dist-info/top_level.txt
arcor2_mocks-1.1.0.dist-info/RECORD
